scrapy_ua_rotator/__init__.py
scrapy_ua_rotator/middleware.py
scrapy_ua_rotator/providers.py
scrapy_ua_rotator-1.0.1.dist-info/licenses/LICENSE
scrapy_ua_rotator-1.0.1.dist-info/METADATA
scrapy_ua_rotator-1.0.1.dist-info/WHEEL
scrapy_ua_rotator-1.0.1.dist-info/top_level.txt
scrapy_ua_rotator-1.0.1.dist-info/RECORD
