Metadata-Version: 2.4
Name: scrapy-ua-rotator
Version: 1.0.1
Summary: Flexible and modern User-Agent rotator middleware for Scrapy, supporting Faker, fake-useragent, and custom providers.
Home-page: https://github.com/geeone/scrapy-ua-rotator
Author: Sergei Denisenko
Author-email: sergei.denisenko@ieee.org
License: MIT
Project-URL: Documentation, https://github.com/geeone/scrapy-ua-rotator
Project-URL: Source, https://github.com/geeone/scrapy-ua-rotator
Project-URL: Bug Tracker, https://github.com/geeone/scrapy-ua-rotator/issues
Keywords: scrapy user-agent middleware rotation fake-useragent faker providers proxy web-scraping
Classifier: Development Status :: 5 - Production/Stable
Classifier: Intended Audience :: Developers
Classifier: License :: OSI Approved :: MIT License
Classifier: Operating System :: OS Independent
Classifier: Programming Language :: Python :: 3
Classifier: Programming Language :: Python :: 3 :: Only
Classifier: Programming Language :: Python :: 3.9
Classifier: Programming Language :: Python :: 3.10
Classifier: Programming Language :: Python :: 3.11
Classifier: Programming Language :: Python :: 3.12
Classifier: Programming Language :: Python :: 3.13
Classifier: Framework :: Scrapy
Classifier: Topic :: Internet :: WWW/HTTP
Classifier: Topic :: Software Development :: Libraries :: Python Modules
Classifier: Topic :: Utilities
Requires-Python: >=3.9
License-File: LICENSE
Requires-Dist: Faker>=36.0.0
Requires-Dist: fake-useragent>=2.0.0
Dynamic: author
Dynamic: author-email
Dynamic: classifier
Dynamic: description
Dynamic: description-content-type
Dynamic: home-page
Dynamic: keywords
Dynamic: license
Dynamic: license-file
Dynamic: project-url
Dynamic: requires-dist
Dynamic: requires-python
Dynamic: summary
